jinjalint/__init__.py
jinjalint/__main__.py
jinjalint/ast.py
jinjalint/check.py
jinjalint/cli.py
jinjalint/config.py
jinjalint/config_test.py
jinjalint/file.py
jinjalint/issue.py
jinjalint/lint.py
jinjalint/lint_test.py
jinjalint/parse.py
jinjalint/parse_test.py
jinjalint/test.py
jinjalint/util.py
jinjalint/util_test.py
jinjalint/version.py
r2c_jinjalint-0.6.2.dist-info/LICENSE
r2c_jinjalint-0.6.2.dist-info/METADATA
r2c_jinjalint-0.6.2.dist-info/WHEEL
r2c_jinjalint-0.6.2.dist-info/entry_points.txt
r2c_jinjalint-0.6.2.dist-info/top_level.txt
r2c_jinjalint-0.6.2.dist-info/RECORD
