Metadata-Version: 2.1
Name: r2c-jinjalint
Version: 0.6.2
Summary: A linter for Jinja-like templates
Home-page: https://github.com/returntocorp/jinjalint/
Author: R2C
Author-email: support@returntocorp.com
License: MIT
Platform: UNKNOWN
Classifier: Development Status :: 3 - Alpha
Classifier: License :: OSI Approved :: MIT License
Classifier: Environment :: Console
Classifier: Intended Audience :: Developers
Classifier: Operating System :: MacOS :: MacOS X
Classifier: Operating System :: Microsoft :: Windows
Classifier: Operating System :: POSIX
Classifier: Programming Language :: Python :: 3.5
Classifier: Programming Language :: Python :: 3.6
Classifier: Programming Language :: Python :: 3.7
Classifier: Programming Language :: Python :: 3.8
Classifier: Topic :: Security
Classifier: Topic :: Software Development :: Quality Assurance
Requires-Dist: parsy (==1.1.0)
Requires-Dist: attrs (==17.2.0)
Requires-Dist: docopt (==0.6.2)
